langchain_memgraph/__init__.py
langchain_memgraph/document_loaders.py
langchain_memgraph/py.typed
langchain_memgraph/retrievers.py
langchain_memgraph/toolkits.py
langchain_memgraph/tools.py
langchain_memgraph/chains/__init__.py
langchain_memgraph/chains/graph_qa.py
langchain_memgraph/chains/prompts.py
langchain_memgraph/graphs/__init__.py
langchain_memgraph/graphs/graph_document.py
langchain_memgraph/graphs/graph_store.py
langchain_memgraph/graphs/memgraph.py
langchain_memgraph-0.1.9.dist-info/METADATA
langchain_memgraph-0.1.9.dist-info/WHEEL
langchain_memgraph-0.1.9.dist-info/licenses/LICENSE
langchain_memgraph-0.1.9.dist-info/RECORD
