Metadata-Version: 2.4
Name: langchain-memgraph
Version: 0.1.9
Summary: An integration package connecting Memgraph and LangChain
Author-email: Ante Javor <ante.javor@memgraph.com>
License: MIT
License-File: LICENSE
Keywords: ai,integration,langchain,memgraph
Classifier: Programming Language :: Python :: 3.10
Classifier: Programming Language :: Python :: 3.11
Classifier: Programming Language :: Python :: 3.12
Requires-Python: >=3.10
Requires-Dist: langchain-core>=0.3.15
Requires-Dist: langchain>=0.3.25
Requires-Dist: memgraph-toolbox>=0.1.6
Requires-Dist: neo4j>=5.28.1
Provides-Extra: test
Requires-Dist: langchain-core>=0.3.67; extra == 'test'
Requires-Dist: langchain-experimental>=0.3.4; extra == 'test'
Requires-Dist: langchain-openai>=0.3.12; extra == 'test'
Requires-Dist: langchain-tests>=0.3.17; extra == 'test'
Requires-Dist: langgraph>=0.3.11; extra == 'test'
Requires-Dist: pytest-asyncio>=0.26.0; extra == 'test'
Requires-Dist: pytest-socket>=0.7.0; extra == 'test'
Requires-Dist: pytest-watcher>=0.3.4; extra == 'test'
Requires-Dist: pytest>=8.3.5; extra == 'test'
Requires-Dist: python-dotenv>=1.0.1; extra == 'test'
